errorpp/__init__.py
errorpp/__main__.py
errorpp-0.0.7.dist-info/METADATA
errorpp-0.0.7.dist-info/WHEEL
errorpp-0.0.7.dist-info/entry_points.txt
errorpp-0.0.7.dist-info/top_level.txt
errorpp-0.0.7.dist-info/RECORD
