Metadata-Version: 2.1
Name: errorpp
Version: 0.0.7
Summary: Automatically propagate the error in an expression symbolically
Home-page: https://github.com/de0ch/errorpp
Author: Deyao Chen
Author-email: chendeyao000@gmail.com
License: UNKNOWN
Project-URL: Bug Tracker, https://github.com/de0ch/errorpp/issues
Platform: UNKNOWN
Classifier: Programming Language :: Python :: 3
Classifier: License :: OSI Approved :: MIT License
Classifier: Operating System :: OS Independent
Requires-Dist: sympy (==1.9)
Requires-Dist: antlr4-python3-runtime (==4.7.2)
